webcvapis/__init__.py
webcvapis/test.py
webcvapis/web_canvas.py
webcvapis-0.0.6.dist-info/LICENSE
webcvapis-0.0.6.dist-info/METADATA
webcvapis-0.0.6.dist-info/WHEEL
webcvapis-0.0.6.dist-info/top_level.txt
webcvapis-0.0.6.dist-info/RECORD
