Metadata-Version: 2.1
Name: webcvapis
Version: 0.0.6
Summary: WebCV APIs
Home-page: https://github.com/qaqFei/webcvapis
Author: qaqFei
Author-email: qaq_fei@163.com
License: MIT License
Classifier: Programming Language :: Python :: 3.12
Classifier: License :: OSI Approved :: MIT License
Classifier: Operating System :: Microsoft :: Windows
Requires-Python: >=3.12.0
License-File: LICENSE
Requires-Dist: pywebview
